iverilog/tobb/lab7/bib3Advanced.v
module bib3Advanced (
    input clk,
    input basla,
    input [8:0] buyruk,
    output reg [3:0] sonuc,
    output reg bitti
);
    integer i, a, b, c, count;
    always@(posedge clk) begin
        if(basla) begin
            bitti <= 1'b0;
            case (buyruk[8:6])
                default: begin
                    sonuc <= 4'b0000;
                end
                3'b000: begin
                    sonuc <= buyruk[5:3] + buyruk[2:0];
                    bitti <= 1'b1;
                end
                3'b001: begin
                    sonuc <= buyruk[5:3] - buyruk[2:0];
                    bitti <= 1'b1;
                end
                3'b010: begin
                    sonuc <= buyruk[5:3] & buyruk[2:0];
                    bitti <= 1'b1;
                end
                3'b011: begin
                    sonuc <= buyruk[5:3] | buyruk[2:0];
                    bitti <= 1'b1;
                end
                3'b100: begin
                    for (i = 0; i <= 4; i++) begin
                        if (buyruk[i] == buyruk[i+1])
                            sonuc <= 4'b1111;
                        else
                            sonuc <= 4'b0000;
                    end
                    bitti <= 1'b1;
                end
                3'b101: begin
                    for (a = 0; a <= 5; a++) begin
                        if (buyruk[a] == 1)
                            sonuc <= 4'b1111;
                        else
                            sonuc <= 4'b0000;
                    end
                    bitti <= 1'b1;
                end
                3'b110: begin
                    count = 0;
                    for (b = 0; b <= 5; b++) begin
                        if (buyruk[b] == 1)
                            count = count + 1;
                    end
                    if (count % 2 == 0)
                        sonuc <= 4'b1111;
                    else
                        sonuc <= 4'b0000;
                    bitti <= 1'b1;
                end
                3'b111: begin
                    count = 0;
                    for (c = 0; c <= 5; c++)
                        if (buyruk[c] == 1)
                            count = count + 1;
                    if (count % 2 == 0)
                        sonuc <= 4'b0000;
                    else
                        sonuc <= 4'b1111;
                    bitti <= 1'b1;
                end
            endcase
        end
        else begin
            bitti <= 1'b0;
            sonuc <= 4'b0000;
        end
    end
endmodule

iverilog/tobb/lab7/bib3AdvancedTB.v
module bib3AdvancedTB();

    reg clk;
    reg basla;
    reg [8:0] buyruk;
    reg [8:0] memory [0:15];
    wire [3:0] sonuc;
    wire bitti;

    bib3Advanced uut (
        .clk(clk),
        .basla(basla),
        .buyruk(buyruk),
        .sonuc(sonuc),
        .bitti(bitti)
    );

always begin
    clk = ~clk; #5;
end

integer i;

initial begin
    $dumpfile("bib3Advanced.vcd");
    $dumpvars;
    clk = 0; basla = 0; buyruk = 9'b0_0000_0000;
    $readmemb("memory.mem", memory); #10;
    basla = 1'b1;

    for(i = 0; i <= 16; i++) begin
        buyruk = memory[i]; #10;
    end

    basla = 1'b0; #10;
    $finish;
end

endmodule

iverilog/tobb/lab7/bib3Advanced.vcd
$date
	Thu Jan 30 07:38:04 2025
$end
$version
	Icarus Verilog
$end
$timescale
	1s
$end
$scope module bib3AdvancedTB $end
$var wire 4 ! sonuc [3:0] $end
$var wire 1 " bitti $end
$var reg 1 # basla $end
$var reg 9 $ buyruk [8:0] $end
$var reg 1 % clk $end
$var integer 32 & i [31:0] $end
$scope module uut $end
$var wire 1 # basla $end
$var wire 9 ' buyruk [8:0] $end
$var wire 1 % clk $end
$var reg 1 " bitti $end
$var reg 4 ( sonuc [3:0] $end
$var integer 32 ) a [31:0] $end
$var integer 32 * b [31:0] $end
$var integer 32 + c [31:0] $end
$var integer 32 , count [31:0] $end
$var integer 32 - i [31:0] $end
$upscope $end
$upscope $end
$enddefinitions $end
#0
$dumpvars
bx -
bx ,
bx +
bx *
bx )
bx (
b0 '
bx &
0%
b0 $
0#
x"
bx !
$end
#5
b0 !
b0 (
0"
1%
#10
0%
b1001 $
b1001 '
b0 &
1#
#15
1"
b10 !
b10 (
1%
#20
0%
b1100001 $
b1100001 '
b1 &
#25
b11 !
b11 (
1"
1%
#30
0%
b10100101 $
b10100101 '
b10 &
#35
b100 !
b100 (
1"
1%
#40
0%
b11100011 $
b11100011 '
b11 &
#45
b111 !
b111 (
1"
1%
#50
0%
b100111111 $
b100111111 '
b100 &
#55
b1111 !
b1111 (
1"
b101 -
1%
#60
0%
b100100001 $
b100100001 '
b101 &
#65
b0 !
b0 (
1"
b101 -
1%
#70
0%
b101100001 $
b101100001 '
b110 &
#75
b1111 !
b1111 (
1"
b110 )
1%
#80
0%
b110100001 $
b110100001 '
b111 &
#85
1"
b110 *
b10 ,
1%
#90
0%
b111100001 $
b111100001 '
b1000 &
#95
b0 !
b0 (
1"
b110 +
b10 ,
1%
#100
0%
b1001 $
b1001 '
b1001 &
#105
b10 !
b10 (
1"
1%
#110
0%
b1100001 $
b1100001 '
b1010 &
#115
b11 !
b11 (
1"
1%
#120
0%
b10100101 $
b10100101 '
b1011 &
#125
b100 !
b100 (
1"
1%
#130
0%
b11100011 $
b11100011 '
b1100 &
#135
b111 !
b111 (
1"
1%
#140
0%
b100111111 $
b100111111 '
b1101 &
#145
b1111 !
b1111 (
1"
b101 -
1%
#150
0%
b100100001 $
b100100001 '
b1110 &
#155
b0 !
b0 (
1"
b101 -
1%
#160
0%
b101100001 $
b101100001 '
b1111 &
#165
b1111 !
b1111 (
1"
b110 )
1%
#170
0%
bx $
bx '
b10000 &
#175
b0 !
b0 (
0"
1%
#180
0%
0#
b10001 &
