lab2/src/fullAdder.v
module fullAdder(
  input A,
  input B,
  input Cin,
  output S,
  output Cout  
);

    wire AB;
    wire ABCin, AaB;

    xor (AB, A, B);
    xor (S, AB, Cin);

    and (ABCin, AB, Cin);
    and (AaB, A, B);

    or (Cout, ABCin, AaB);

endmodule

labs/lab2/src/ftb.v
module ftb ();

reg r1, r2, r3;
wire w1, w2;

fullAdder uut(
    .A(r1),
    .B(r2),
    .Cin(r3),
    .S(w1),
    .Cout(w2)
);

initial begin
    $dumpfile("fdmp.vcd");
    $dumpvars;
    r1 = 0; r2 = 0; r3 = 0; #10
    r1 = 0; r2 = 0; r3 = 1; #10
    r1 = 0; r2 = 1; r3 = 0; #10
    r1 = 0; r2 = 1; r3 = 1; #10
    r1 = 1; r2 = 0; r3 = 0; #10
    r1 = 1; r2 = 0; r3 = 1; #10
    r1 = 1; r2 = 1; r3 = 0; #10
    r1 = 1; r2 = 1; r3 = 1; #10
    $display(w1);
    $display(w2);
end

endmodule

lab2/src/fdmp.vcd
$date
	Thu Apr 11 07:39:27 2024
$end
$version
	Icarus Verilog
$end
$timescale
	1s
$end
$scope module ftb $end
$var wire 1 ! w2 $end
$var wire 1 " w1 $end
$var reg 1 # r1 $end
$var reg 1 $ r2 $end
$var reg 1 % r3 $end
$scope module uut $end
$var wire 1 # A $end
$var wire 1 & AB $end
$var wire 1 ' ABCin $end
$var wire 1 ( AaB $end
$var wire 1 $ B $end
$var wire 1 % Cin $end
$var wire 1 ! Cout $end
$var wire 1 " S $end
$upscope $end
$upscope $end
$enddefinitions $end
$comment Show the parameter values. $end
$dumpall
$end
#0
$dumpvars
0(
0'
0&
0%
0$
0#
0"
0!
$end
#10
1"
1%
#20
1&
0%
1$
#30
1!
0"
1'
1%
#40
0!
1"
0'
0%
0$
1#
#50
1!
0"
1'
1%
#60
0'
0&
1(
0%
1$
#70
1"
1%
