iverilog/tobb/labs/lab3/src/halfAdder.v
module halfAdder(
    input A, B,
    output S, C
);

xor(S, A, B);
and(C, A, B);

endmodule

iverilog/tobb/labs/lab3/src/mult2bit.v
module mult2bit (
    input [1:0] A,
    input [1:0] B,
    output [3:0] C
);

wire c1, c2, c4, c5;

and a0(c1, A[1], B[0]);
and a1(c2, A[0], B[1]);
and a2(c5, A[1], B[1]);
and a3(C[0], A[0], B[0]);

halfAdder h0(c1, c2, C[1], c4);
halfAdder h1(c5, c4, C[3], C[2]);

endmodule

iverilog/tobb/labs/lab3/src/mtb.v
module mtb();

reg[1:0] A, B;
wire [3:0] C;
mult2bit uut(A,B,C);

initial begin
    $dumpfile("3dmp.vcd");
    $dumpvars;

	A = 2'd0; B = 2'd3; #10;
	A = 2'd1; B = 2'd2; #10;
    A = 2'd2; B = 2'd1; #10;
    A = 2'd3; B = 2'd0; #10;

    A = 2'd0; B = 2'd0; #10;
    A = 2'd1; B = 2'd1; #10;
    A = 2'd2; B = 2'd2; #10;
    A = 2'd3; B = 2'd3; #10;

end

endmodule

iverilog/tobb/labs/lab3/src/fullAdder.v
module fullAdder(
    input A, B, Z,
    output S, C
);
    wire W0, W1, W2;

halfAdder h0(A, B, W0, W1);
halfAdder h1(W0, Z, S, W2);

or(C, W1, W2);

endmodule

iverilog/tobb/labs/lab3/src/3dmp.vcd
$date
	Sat May 04 01:15:09 2024
$end
$version
	Icarus Verilog
$end
$timescale
	1s
$end
$scope module fullAdder $end
$var wire 1 ! A $end
$var wire 1 " B $end
$var wire 1 # C $end
$var wire 1 $ Z $end
$var wire 1 % W2 $end
$var wire 1 & W1 $end
$var wire 1 ' W0 $end
$var wire 1 ( S $end
$scope module h0 $end
$var wire 1 ! A $end
$var wire 1 " B $end
$var wire 1 & C $end
$var wire 1 ' S $end
$upscope $end
$scope module h1 $end
$var wire 1 ' A $end
$var wire 1 $ B $end
$var wire 1 % C $end
$var wire 1 ( S $end
$upscope $end
$upscope $end
$scope module mtb $end
$var wire 4 ) C [3:0] $end
$var reg 2 * A [1:0] $end
$var reg 2 + B [1:0] $end
$scope module uut $end
$var wire 2 , A [1:0] $end
$var wire 2 - B [1:0] $end
$var wire 1 . c1 $end
$var wire 1 / c2 $end
$var wire 1 0 c5 $end
$var wire 1 1 c4 $end
$var wire 4 2 C [3:0] $end
$scope module h0 $end
$var wire 1 . A $end
$var wire 1 / B $end
$var wire 1 1 C $end
$var wire 1 3 S $end
$upscope $end
$scope module h1 $end
$var wire 1 0 A $end
$var wire 1 1 B $end
$var wire 1 4 C $end
$var wire 1 5 S $end
$upscope $end
$upscope $end
$upscope $end
$enddefinitions $end
$comment Show the parameter values. $end
$dumpall
$end
#0
$dumpvars
05
04
03
b0 2
01
00
0/
0.
b11 -
b0 ,
b11 +
b0 *
b0 )
x(
x'
x&
x%
z$
x#
z"
z!
$end
#10
b10 )
b10 2
13
1/
b10 +
b10 -
b1 *
b1 ,
#20
1.
0/
b1 +
b1 -
b10 *
b10 ,
#30
b0 )
b0 2
03
0.
b0 +
b0 -
b11 *
b11 ,
#40
b0 *
b0 ,
#50
b1 )
b1 2
b1 +
b1 -
b1 *
b1 ,
#60
15
10
b1000 )
b1000 2
b10 +
b10 -
b10 *
b10 ,
#70
05
14
11
1.
1/
b101 )
b101 2
b11 +
b11 -
b11 *
b11 ,
