iverilog/tobb/lab5/sayac.v
module sayac (
    input clk, rst, en,
    input [2:0] sayma_miktari,
    input sayma_yonu,
    output reg [5:0] sayac
);

    reg [1:0] clk_divider;
    reg [2:0] miktar;

    initial begin
        sayac = 6'b0000_00;
        miktar = 3'b001;
        clk_divider = 2'b00;
    end

    always@(*) begin
    miktar = sayma_miktari;
    end

    always@(negedge clk or posedge rst) begin
        if (rst) begin
            sayac <= 6'b0000_00;
            clk_divider <= 2'b00;
        end else begin
            clk_divider <= clk_divider + 1;
        end

        if (clk_divider == 2'b11) begin
            clk_divider <= 2'b00;
            if (en) begin
                if (sayma_miktari) begin
                    if (sayac + miktar >= 6'b1111_11) begin
                        sayac <= 6'b1111_11;
                    end else begin
                        sayac <= sayac + miktar;
                    end
                end else begin
                    if (miktar >= sayac) begin
                        sayac <= 6'b0000_00;
                    end else begin
                        sayac <= sayac - miktar;
                    end
                end
            end
        end
    end
endmodule

iverilog/tobb/lab5/ayarliSayacTB.v
module ayarliSayacTB();

    reg clk, rst, en;
    reg [2:0] sayma_miktari;
    reg sayma_yonu;
    wire [5:0] sayac;

sayac uut (
    .clk(clk),
    .rst(rst),
    .en(en),
    .sayma_miktari(sayma_miktari),
    .sayma_yonu(sayma_yonu),
    .sayac(sayac)
);

always begin
    clk = ~clk; #1;
end

initial begin
    $dumpfile("ayarliSayac.vcd");
    $dumpvars;
    clk = 1; rst = 0; en = 1; sayma_miktari = 3'b111; sayma_yonu = 1'b1; #32;
    clk = 1; rst = 0; en = 1; sayma_miktari = 3'b111; sayma_yonu = 1'b1; #8;
    clk = 1; rst = 0; en = 1; sayma_miktari = 3'b111; sayma_yonu = 1'b1; #64;
    clk = 1; rst = 0; en = 1; sayma_miktari = 3'b111; sayma_yonu = 1'b1; #16;
    clk = 1; rst = 1; en = 1; sayma_miktari = 3'b010; sayma_yonu = 1'b1; #8;
    $finish;
end

endmodule

iverilog/tobb/lab5/ayarliSayac.vcd
$date
	Sun Jan 26 04:55:11 2025
$end
$version
	Icarus Verilog
$end
$timescale
	1s
$end
$scope module ayarliSayacTB $end
$var wire 6 ! sayac [5:0] $end
$var reg 1 " clk $end
$var reg 1 # en $end
$var reg 1 $ rst $end
$var reg 3 % sayma_miktari [2:0] $end
$var reg 1 & sayma_yonu $end
$scope module uut $end
$var wire 1 " clk $end
$var wire 1 # en $end
$var wire 1 $ rst $end
$var wire 3 ' sayma_miktari [2:0] $end
$var wire 1 & sayma_yonu $end
$var reg 2 ( clk_divider [1:0] $end
$var reg 3 ) miktar [2:0] $end
$var reg 6 * sayac [5:0] $end
$upscope $end
$upscope $end
$enddefinitions $end
#0
$dumpvars
b0 *
b0 )
b0 (
b111 '
1&
b111 %
0$
1#
1"
b0 !
$end
#1
b1 (
0"
#2
1"
#3
b10 (
0"
#4
1"
#5
b11 (
0"
#6
1"
#7
b111 )
b0 (
0"
#8
1"
#9
b1 (
0"
#10
1"
#11
b10 (
0"
#12
1"
#13
b11 (
0"
#14
1"
#15
b111 !
b111 *
b0 (
0"
#16
1"
#17
b1 (
0"
#18
1"
#19
b10 (
0"
#20
1"
#21
b11 (
0"
#22
1"
#23
b1110 !
b1110 *
b0 (
0"
#24
1"
#25
b1 (
0"
#26
1"
#27
b10 (
0"
#28
1"
#29
b11 (
0"
#30
1"
#31
b10101 !
b10101 *
b0 (
0"
#32
b1 (
0"
#33
1"
#34
b10 (
0"
#35
1"
#36
b11 (
0"
#37
1"
#38
b11100 !
b11100 *
b0 (
0"
#39
1"
#40
b1 (
0"
#41
1"
#42
b10 (
0"
#43
1"
#44
b11 (
0"
#45
1"
#46
b100011 !
b100011 *
b0 (
0"
#47
1"
#48
b1 (
0"
#49
1"
#50
b10 (
0"
#51
1"
#52
b11 (
0"
#53
1"
#54
b101010 !
b101010 *
b0 (
0"
#55
1"
#56
b1 (
0"
#57
1"
#58
b10 (
0"
#59
1"
#60
b11 (
0"
#61
1"
#62
b110001 !
b110001 *
b0 (
0"
#63
1"
#64
b1 (
0"
#65
1"
#66
b10 (
0"
#67
1"
#68
b11 (
0"
#69
1"
#70
b111000 !
b111000 *
b0 (
0"
#71
1"
#72
b1 (
0"
#73
1"
#74
b10 (
0"
#75
1"
#76
b11 (
0"
#77
1"
#78
b111111 !
b111111 *
b0 (
0"
#79
1"
#80
b1 (
0"
#81
1"
#82
b10 (
0"
#83
1"
#84
b11 (
0"
#85
1"
#86
b110 !
b110 *
b0 (
0"
#87
1"
#88
b1 (
0"
#89
1"
#90
b10 (
0"
#91
1"
#92
b11 (
0"
#93
1"
#94
b1101 !
b1101 *
b0 (
0"
#95
1"
#96
b1 (
0"
#97
1"
#98
b10 (
0"
#99
1"
#100
b11 (
0"
#101
1"
#102
b10100 !
b10100 *
b0 (
0"
#103
1"
#104
b1 (
0"
#105
1"
#106
b10 (
0"
#107
1"
#108
b11 (
0"
#109
1"
#110
b11011 !
b11011 *
b0 (
0"
#111
1"
#112
b1 (
0"
#113
1"
#114
b10 (
0"
#115
1"
#116
b11 (
0"
#117
1"
#118
b100010 !
b100010 *
b0 (
0"
#119
1"
#120
b0 )
b0 !
b0 *
0"
b10 %
b10 '
1$
