iverilog/tobb/lab5/ayarliSayac.v
module ayarliSayac (
    input clk, rst, en,
    input [2:0] sayma_miktari,
    input sayma_yonu,
    output reg [5:0] sayac
);

    reg [2:0] miktar;
    reg [1:0] clk_divider;

    initial begin
        sayac = 6'b0000_00;
        miktar = 3'b001;
        clk_divider = 2'b00;
    end

    always @(negedge clk or posedge rst) begin
        if (rst) begin
            sayac <= 6'b0000_00;
            clk_divider <= 2'b00;
        end else begin
            clk_divider <= clk_divider + 1;
        end
        if (clk_divider == 2'b11) begin
            if (en) begin
            miktar <= sayma_miktari;
            if (sayma_yonu == 1) begin
                if (sayac + miktar >= 6'b1111_11) begin
                    sayac <= 6'b1111_11;
                end else begin
                    sayac <= miktar + sayac;
                end
            end else begin
                if (sayac - miktar <= 6'b0000_00) begin
                    sayac <= 6'b0000_00;
                end else begin
                    sayac <= sayac - miktar;
                end
            end
        end
    end
end
endmodule

iverilog/tobb/lab5/ayarliSayacTB.v
module ayarliSayacTB();

    reg clk, rst, en;
    reg [2:0] sayma_miktari;
    reg sayma_yonu;
    wire [5:0] sayac;

ayarliSayac uut (
    .clk(clk),
    .rst(rst),
    .en(en),
    .sayma_miktari(sayma_miktari),
    .sayma_yonu(sayma_yonu),
    .sayac(sayac)
);

always begin
    clk = ~clk; #1;
end

initial begin
    $dumpfile("ayarliSayac.vcd");
    $dumpvars;
    clk = 0; rst = 0; en = 1; sayma_miktari = 3'b110; sayma_yonu = 1'b1; #16;
    clk = 1; rst = 0; en = 0; sayma_miktari = 3'b010; sayma_yonu = 1'b1; #8;
    clk = 1; rst = 0; en = 1; sayma_miktari = 3'b011; sayma_yonu = 1'b1; #8;
    clk = 1; rst = 1; en = 1; sayma_miktari = 3'b010; sayma_yonu = 1'b1; #8;
    $finish;
end

endmodule

iverilog/tobb/lab5/ayarliSayac.vcd
$date
	Sat Jan 25 07:58:46 2025
$end
$version
	Icarus Verilog
$end
$timescale
	1s
$end
$scope module ayarliSayacTB $end
$var wire 6 ! sayac [5:0] $end
$var reg 1 " clk $end
$var reg 1 # en $end
$var reg 1 $ rst $end
$var reg 3 % sayma_miktari [2:0] $end
$var reg 1 & sayma_yonu $end
$scope module uut $end
$var wire 1 " clk $end
$var wire 1 # en $end
$var wire 1 $ rst $end
$var wire 3 ' sayma_miktari [2:0] $end
$var wire 1 & sayma_yonu $end
$var reg 2 ( clk_divider [1:0] $end
$var reg 3 ) miktar [2:0] $end
$var reg 6 * sayac [5:0] $end
$upscope $end
$upscope $end
$enddefinitions $end
#0
$dumpvars
b0 *
b1 )
b1 (
b110 '
1&
b110 %
0$
1#
0"
b0 !
$end
#1
1"
#2
b10 (
0"
#3
1"
#4
b11 (
0"
#5
1"
#6
b1 !
b1 *
b110 )
b0 (
0"
#7
1"
#8
b1 (
0"
#9
1"
#10
b10 (
0"
#11
1"
#12
b11 (
0"
#13
1"
#14
b111 !
b111 *
b0 (
0"
#15
1"
#16
b1 (
0"
b10 %
b10 '
0#
#17
1"
#18
b10 (
0"
#19
1"
#20
b11 (
0"
#21
1"
#22
b0 (
0"
#23
1"
#24
b1 (
0"
b11 %
b11 '
1#
#25
1"
#26
b10 (
0"
#27
1"
#28
b11 (
0"
#29
1"
#30
b1101 !
b1101 *
b11 )
b0 (
0"
#31
1"
#32
b0 !
b0 *
0"
b10 %
b10 '
1$
