iverilog/tobb/lab5/tetris.v
module tetris (
    input [2:0] parca,
    input clk,
    output reg [3:0] yukseklik,
    output reg bitti_mi,
    output reg [3:0] cevrim
);

    reg [3:0] yukseklik1, yukseklik2, yukseklik3;
    initial begin
        cevrim = 4'd0;
        bitti_mi = 1'b0;
        yukseklik = 4'b0;
        yukseklik1 = 4'd0;
        yukseklik2 = 4'd0;
        yukseklik3 = 4'd0;
    end


    always@(posedge clk) begin
        if (!bitti_mi) begin
            if (parca[0]) begin
            yukseklik1 <= yukseklik1 + 1;
            end if (parca[1]) begin
                yukseklik2 <= yukseklik2 + 1;
            end if (parca[2]) begin
                yukseklik3 <= yukseklik3 + 1;
            end
         cevrim <= cevrim + 1;

         if (cevrim == 4'd15) begin
            bitti_mi <= 1'b1;
         end
    end
end

always@(posedge clk) begin //comperator
    if (bitti_mi) begin
        if (yukseklik1 >= yukseklik2 && yukseklik1 >= yukseklik3) begin
            yukseklik <= yukseklik1;
        end else if (yukseklik2 >= yukseklik1 && yukseklik2 >= yukseklik3) begin
            yukseklik <= yukseklik2;
        end else begin
            yukseklik <= yukseklik3;
        end
    end
end

endmodule

iverilog/tobb/lab5/tetrisTB.v
module tetrisTB();

    reg [2:0] p;
    reg clk;
    wire [3:0] yukseklik;
    wire bitti_mi;
    wire [3:0] cevrim;

tetris uut (
    .parca(p),
    .clk(clk),
    .yukseklik(yukseklik),
    .bitti_mi(bitti_mi),
    .cevrim(cevrim)
);

    always begin
        clk = ~clk; #1;
    end

initial begin
    $dumpfile("tetris.vcd");
    $dumpvars;
    clk = 0; p = 3'b010; #2;
    p = 3'b011; #2;
    p = 3'b010; #2;
    p = 3'b000; #30;
    $finish;
end

endmodule

iverilog/tobb/lab5/tetris.vcd
$date
	Sun Jan 26 06:03:11 2025
$end
$version
	Icarus Verilog
$end
$timescale
	1s
$end
$scope module tetrisTB $end
$var wire 4 ! yukseklik [3:0] $end
$var wire 4 " cevrim [3:0] $end
$var wire 1 # bitti_mi $end
$var reg 1 $ clk $end
$var reg 3 % p [2:0] $end
$scope module uut $end
$var wire 1 $ clk $end
$var wire 3 & parca [2:0] $end
$var reg 1 # bitti_mi $end
$var reg 4 ' cevrim [3:0] $end
$var reg 4 ( yukseklik [3:0] $end
$var reg 4 ) yukseklik1 [3:0] $end
$var reg 4 * yukseklik2 [3:0] $end
$var reg 4 + yukseklik3 [3:0] $end
$upscope $end
$upscope $end
$enddefinitions $end
#0
$dumpvars
b0 +
b0 *
b0 )
b0 (
b0 '
b10 &
b10 %
0$
0#
b0 "
b0 !
$end
#1
b1 "
b1 '
b1 *
1$
#2
0$
b11 %
b11 &
#3
b10 "
b10 '
b10 *
b1 )
1$
#4
0$
b10 %
b10 &
#5
b11 "
b11 '
b11 *
1$
#6
0$
b0 %
b0 &
#7
b100 "
b100 '
1$
#8
0$
#9
b101 "
b101 '
1$
#10
0$
#11
b110 "
b110 '
1$
#12
0$
#13
b111 "
b111 '
1$
#14
0$
#15
b1000 "
b1000 '
1$
#16
0$
#17
b1001 "
b1001 '
1$
#18
0$
#19
b1010 "
b1010 '
1$
#20
0$
#21
b1011 "
b1011 '
1$
#22
0$
#23
b1100 "
b1100 '
1$
#24
0$
#25
b1101 "
b1101 '
1$
#26
0$
#27
b1110 "
b1110 '
1$
#28
0$
#29
b1111 "
b1111 '
1$
#30
0$
#31
1#
b0 "
b0 '
1$
#32
0$
#33
b11 !
b11 (
1$
