iverilog/nand2tetris/nands/and16/andGate.v
module andGate (
   input  A_i,
   input  B_i,
   output Y_o
);

   wire nand_out;

   nand nand1 (nand_out, A_i, B_i);
   nand nand2 (Y_o, nand_out, nand_out);

endmodule

iverilog/nand2tetris/nands/and16/andSixTGate.v
module andSixTGate(
    input [15:0] A_i,
    input [15:0] B_i,
    output [15:0] Y_o
);

andGate a0(A_i[0], B_i[0], Y_o[0]);
andGate a1(A_i[1], B_i[1], Y_o[1]);
andGate a2(A_i[2], B_i[2], Y_o[2]);
andGate a3(A_i[3], B_i[3], Y_o[3]);
andGate a4(A_i[4], B_i[4], Y_o[4]);
andGate a5(A_i[5], B_i[5], Y_o[5]);
andGate a6(A_i[6], B_i[6], Y_o[6]);
andGate a7(A_i[7], B_i[7], Y_o[7]);
andGate a8(A_i[8], B_i[8], Y_o[8]);
andGate a9(A_i[9], B_i[9], Y_o[9]);
andGate a10(A_i[10], B_i[10], Y_o[10]);
andGate a11(A_i[11], B_i[11], Y_o[11]);
andGate a12(A_i[12], B_i[12], Y_o[12]);
andGate a13(A_i[13], B_i[13], Y_o[13]);
andGate a14(A_i[14], B_i[14], Y_o[14]);
andGate a15(A_i[15], B_i[15], Y_o[15]);

endmodule

iverilog/nand2tetris/nands/and16/andSixTGateTB.v
module andSixTGateTB();
    reg [15:0] A_i;
    reg [15:0] B_i;
    wire [15:0] Y_o;

    andSixTGate uut(
        .A_i(A_i),
        .B_i(B_i),
        .Y_o(Y_o)
);

initial begin
    $dumpfile("andSixTGate.vcd");
    $dumpvars;
    A_i = 16'b0000_0000_0000_0000; B_i = 16'b0000_0000_0000_0000; #10;
    A_i = 16'b0000_0000_0000_0000; B_i = 16'b0000_0000_0000_0001; #10;
    A_i = 16'b0000_0000_0000_0001; B_i = 16'b0000_0000_0000_0001; #10;
    A_i = 16'b0000_0000_0100_0000; B_i = 16'b0000_0000_0000_0000; #10;
    A_i = 16'b0000_0000_0100_0000; B_i = 16'b0000_0000_0100_0000; #10;
    A_i = 16'b0000_0000_0000_0000; B_i = 16'b0000_0010_0000_0000; #10;
    A_i = 16'b0000_0010_0000_0000; B_i = 16'b0000_0010_0000_0000; #10;
    A_i = 16'b1111_1111_1111_1111; B_i = 16'b1111_1111_1111_1111; #10;
    $finish;
end

endmodule

iverilog/nand2tetris/nands/and16/andSixTGate.vcd
$date
	Tue Dec 10 00:39:27 2024
$end
$version
	Icarus Verilog
$end
$timescale
	1s
$end
$scope module andSixTGateTB $end
$var wire 16 ! Y_o [15:0] $end
$var reg 16 " A_i [15:0] $end
$var reg 16 # B_i [15:0] $end
$scope module uut $end
$var wire 16 $ A_i [15:0] $end
$var wire 16 % B_i [15:0] $end
$var wire 16 & Y_o [15:0] $end
$scope module a0 $end
$var wire 1 ' A_i $end
$var wire 1 ( B_i $end
$var wire 1 ) Y_o $end
$var wire 1 * nand_out $end
$upscope $end
$scope module a1 $end
$var wire 1 + A_i $end
$var wire 1 , B_i $end
$var wire 1 - Y_o $end
$var wire 1 . nand_out $end
$upscope $end
$scope module a10 $end
$var wire 1 / A_i $end
$var wire 1 0 B_i $end
$var wire 1 1 Y_o $end
$var wire 1 2 nand_out $end
$upscope $end
$scope module a11 $end
$var wire 1 3 A_i $end
$var wire 1 4 B_i $end
$var wire 1 5 Y_o $end
$var wire 1 6 nand_out $end
$upscope $end
$scope module a12 $end
$var wire 1 7 A_i $end
$var wire 1 8 B_i $end
$var wire 1 9 Y_o $end
$var wire 1 : nand_out $end
$upscope $end
$scope module a13 $end
$var wire 1 ; A_i $end
$var wire 1 < B_i $end
$var wire 1 = Y_o $end
$var wire 1 > nand_out $end
$upscope $end
$scope module a14 $end
$var wire 1 ? A_i $end
$var wire 1 @ B_i $end
$var wire 1 A Y_o $end
$var wire 1 B nand_out $end
$upscope $end
$scope module a15 $end
$var wire 1 C A_i $end
$var wire 1 D B_i $end
$var wire 1 E Y_o $end
$var wire 1 F nand_out $end
$upscope $end
$scope module a2 $end
$var wire 1 G A_i $end
$var wire 1 H B_i $end
$var wire 1 I Y_o $end
$var wire 1 J nand_out $end
$upscope $end
$scope module a3 $end
$var wire 1 K A_i $end
$var wire 1 L B_i $end
$var wire 1 M Y_o $end
$var wire 1 N nand_out $end
$upscope $end
$scope module a4 $end
$var wire 1 O A_i $end
$var wire 1 P B_i $end
$var wire 1 Q Y_o $end
$var wire 1 R nand_out $end
$upscope $end
$scope module a5 $end
$var wire 1 S A_i $end
$var wire 1 T B_i $end
$var wire 1 U Y_o $end
$var wire 1 V nand_out $end
$upscope $end
$scope module a6 $end
$var wire 1 W A_i $end
$var wire 1 X B_i $end
$var wire 1 Y Y_o $end
$var wire 1 Z nand_out $end
$upscope $end
$scope module a7 $end
$var wire 1 [ A_i $end
$var wire 1 \ B_i $end
$var wire 1 ] Y_o $end
$var wire 1 ^ nand_out $end
$upscope $end
$scope module a8 $end
$var wire 1 _ A_i $end
$var wire 1 ` B_i $end
$var wire 1 a Y_o $end
$var wire 1 b nand_out $end
$upscope $end
$scope module a9 $end
$var wire 1 c A_i $end
$var wire 1 d B_i $end
$var wire 1 e Y_o $end
$var wire 1 f nand_out $end
$upscope $end
$upscope $end
$upscope $end
$enddefinitions $end
#0
$dumpvars
1f
0e
0d
0c
1b
0a
0`
0_
1^
0]
0\
0[
1Z
0Y
0X
0W
1V
0U
0T
0S
1R
0Q
0P
0O
1N
0M
0L
0K
1J
0I
0H
0G
1F
0E
0D
0C
1B
0A
0@
0?
1>
0=
0<
0;
1:
09
08
07
16
05
04
03
12
01
00
0/
1.
0-
0,
0+
1*
0)
0(
0'
b0 &
b0 %
b0 $
b0 #
b0 "
b0 !
$end
#10
1(
b1 #
b1 %
#20
b1 !
b1 &
1)
0*
1'
b1 "
b1 $
#30
b0 !
b0 &
0)
1*
0(
0'
1W
b0 #
b0 %
b1000000 "
b1000000 $
#40
b1000000 !
b1000000 &
1Y
0Z
1X
b1000000 #
b1000000 %
#50
b0 !
b0 &
0Y
1Z
0X
1d
0W
b1000000000 #
b1000000000 %
b0 "
b0 $
#60
b1000000000 !
b1000000000 &
1e
0f
1c
b1000000000 "
b1000000000 $
#70
1)
1-
1I
1M
1Q
1U
1Y
1]
1a
11
15
19
1=
1A
b1111111111111111 !
b1111111111111111 &
1E
0*
0.
0J
0N
0R
0V
0Z
0^
0b
02
06
0:
0>
0B
0F
1(
1,
1H
1L
1P
1T
1X
1\
1`
10
14
18
1<
1@
1D
1'
1+
1G
1K
1O
1S
1W
1[
1_
1/
13
17
1;
1?
1C
b1111111111111111 #
b1111111111111111 %
b1111111111111111 "
b1111111111111111 $
