iverilog/tobb/lab4/bib3.v
module  bib3 (
    input [8:0] buyruk,
    output reg [3:0] sonuc
);
    integer i, a, b, c, count;
    always@(buyruk) begin
        case (buyruk[8:6])
        default: sonuc = 4'b0000;
        3'b000: sonuc = buyruk[5:3] + buyruk[2:0];
        3'b001: sonuc = buyruk[5:3] - buyruk[2:0];
        3'b010: sonuc = buyruk[5:3] & buyruk[2:0];
        3'b011: sonuc = buyruk[5:3] | buyruk[2:0];
        3'b100: begin
            for (i = 0; i <= 4; i++)
                if (buyruk[i] == buyruk[i+1])
                    sonuc = 4'b1111;
                else
                    sonuc = 4'b0000;
        end
        3'b101: for (a = 0; a <= 5; a++) begin
                            if (buyruk[a] == 1)
                                sonuc = 4'b1111;
                            else
                            sonuc = 4'b0000;
        end
        3'b110: begin
             count = 0;
            for (b = 0; b <= 5; b++) begin
                if (buyruk[b] == 1)
                    count = count + 1;
            end
            if (count % 2 == 0)
                sonuc = 4'b1111;
            else
                sonuc = 4'b0000;
        end
        3'b111: begin
             count = 0;
            for (c = 0; c <= 5; c++)
                if (buyruk[c] == 1)
                count++;
                if (count % 2 == 0)
                    sonuc = 4'b0000;
                else
                    sonuc = 4'b1111;
        end
        endcase
    end
endmodule

iverilog/tobb/lab4/bib3TB.v
module bib3TB();

reg [8:0] A;
wire [3:0] Y;

bib3 uut (
    .buyruk(A),
    .sonuc(Y)
);

initial begin
    $dumpfile("bib3.vcd");
    $dumpvars;
    A = 9'b000_001_001; #5;
    A = 9'b001_100_001; #5;
    A = 9'b010_100_101; #5;
    A = 9'b011_100_011; #5;
    A = 9'b100_111_111; #5;
    A = 9'b100_100_001; #5;
    A = 9'b101_100_001; #5;
    A = 9'b110_100_001; #5;
    A = 9'b111_100_001; #5;
end

endmodule

iverilog/tobb/lab4/bib3.vcd
$date
	Sat Jan 25 01:26:43 2025
$end
$version
	Icarus Verilog
$end
$timescale
	1s
$end
$scope module bib3TB $end
$var wire 4 ! Y [3:0] $end
$var reg 9 " A [8:0] $end
$scope module uut $end
$var wire 9 # buyruk [8:0] $end
$var reg 4 $ sonuc [3:0] $end
$var integer 32 % a [31:0] $end
$var integer 32 & b [31:0] $end
$var integer 32 ' c [31:0] $end
$var integer 32 ( count [31:0] $end
$var integer 32 ) i [31:0] $end
$upscope $end
$upscope $end
$enddefinitions $end
#0
$dumpvars
bx )
bx (
bx '
bx &
bx %
b10 $
b1001 #
b1001 "
b10 !
$end
#5
b11 !
b11 $
b1100001 "
b1100001 #
#10
b100 !
b100 $
b10100101 "
b10100101 #
#15
b111 !
b111 $
b11100011 "
b11100011 #
#20
b1111 !
b1111 $
b101 )
b100111111 "
b100111111 #
#25
b0 !
b0 $
b101 )
b100100001 "
b100100001 #
#30
b1111 !
b1111 $
b110 %
b101100001 "
b101100001 #
#35
b110 &
b10 (
b110100001 "
b110100001 #
#40
b0 !
b0 $
b110 '
b10 (
b111100001 "
b111100001 #
