project/opCode.v
module opCode (
    input A, B, C,
    output [7:0] opCode
);
    wire and1, and2, and3, and4, notA, notB, notC;

    not n1(notA, A);
    not n2(notB, B);
    not n3(notC, C);

    and a01(and1, A, B);
    and a02(and2, notA, B);
    and a03(and3, A, notB);
    and a04(and4, notA, notB);

    and a1(opCode[0], and4, notC);
    and a2(opCode[1], and4, C);
    and a3(opCode[2], and2, notC);
    and a4(opCode[3], and2, C);
    and a5(opCode[4], and3, notC);
    and a6(opCode[5], and3, C);
    and a7(opCode[6], and1, notC);
    and a8(opCode[7], and1, C);

endmodule

project/opCodeTB.v
module opCodeTB();

reg A, B, C;
wire [7:0] opCode;

opCode uut (
    .A(A),
    .B(B),
    .C(C),
    .opCode(opCode)
);

initial begin
    $dumpfile("opCode.vcd");
    $dumpvars;
    A = 1'b0; B = 1'b0; C = 1'b0; #3;
    A = 1'b0; B = 1'b0; C = 1'b1; #3;
    A = 1'b0; B = 1'b1; C = 1'b0; #3;
    A = 1'b0; B = 1'b1; C = 1'b1; #3;
    A = 1'b1; B = 1'b0; C = 1'b0; #3;
    A = 1'b1; B = 1'b0; C = 1'b1; #3;
    A = 1'b1; B = 1'b1; C = 1'b0; #3;
    A = 1'b1; B = 1'b1; C = 1'b1; #3;
    $finish;
end

endmodule

project/opCode.vcd
$date
	Sun Dec 15 00:28:47 2024
$end
$version
	Icarus Verilog
$end
$timescale
	1s
$end
$scope module opCodeTB $end
$var wire 8 ! opCode [7:0] $end
$var reg 1 " A $end
$var reg 1 # B $end
$var reg 1 $ C $end
$scope module uut $end
$var wire 1 " A $end
$var wire 1 # B $end
$var wire 1 $ C $end
$var wire 1 % and1 $end
$var wire 1 & and2 $end
$var wire 1 ' and3 $end
$var wire 1 ( and4 $end
$var wire 1 ) notA $end
$var wire 1 * notB $end
$var wire 1 + notC $end
$var wire 8 , opCode [7:0] $end
$upscope $end
$upscope $end
$enddefinitions $end
#0
$dumpvars
b1 ,
1+
1*
1)
1(
0'
0&
0%
0$
0#
0"
b1 !
$end
#3
0+
b10 !
b10 ,
1$
#6
0(
1+
b100 !
b100 ,
0*
1&
0$
1#
#9
0+
b1000 !
b1000 ,
1$
#12
1'
1+
b10000 !
b10000 ,
1*
0&
0)
0$
0#
1"
#15
0+
b100000 !
b100000 ,
1$
#18
0'
1+
b1000000 !
b1000000 ,
0*
1%
0$
1#
#21
0+
b10000000 !
b10000000 ,
1$
