labs/lab2_prep/src/lab2.v
module lab2(
     input A,
     input B,
     input C,
     input D,
     output F
     );

     wire An, Bn, Cn;
     wire AnBC, AD, CnD;

     not n1 (An, A);
     and (AnBC, An, B, C);

     not (Bn, B);
     and (AD, A, D);

     not (Cn, C);
     and (CnD, Cn, D);

     or (F, AnBC, Bn, AD, CnD);


endmodule

labs/lab2_prep/src/tb.v
module tb();

reg r1, r2, r3, r4;
wire w1;
    
lab2 uut(
    .A(r1),
    .B(r2),
    .C(r3),
    .D(r4),
    .F(w1)
);

// test uut(r1, r2, w1, w2, w3);

initial begin
    $dumpfile("dmp.vcd");
    $dumpvars;
    r1 = 1'b0; r2 = 1'b0; r3 = 1'b0; r4 = 1'b0;  #50;
    r1 = 1'b0; r2 = 1'b0; r3 = 1'b0; r4 = 1'b1;  #50;
    r1 = 1'b0; r2 = 1'b0; r3 = 1'b1; r4 = 1'b0;  #50;
    r1 = 1'b0; r2 = 1'b0; r3 = 1'b1; r4 = 1'b1;  #50;
    r1 = 1'b0; r2 = 1'b1; r3 = 1'b0; r4 = 1'b0;  #50;
    r1 = 1'b0; r2 = 1'b1; r3 = 1'b0; r4 = 1'b1;  #50;
    r1 = 1'b0; r2 = 1'b1; r3 = 1'b1; r4 = 1'b0;  #50;
    r1 = 1'b0; r2 = 1'b1; r3 = 1'b1; r4 = 1'b1;  #50;
    $display(w1);
end



endmodule

labs/lab2_prep/src/dmp.vcd
$date
	Thu Apr 11 06:20:47 2024
$end
$version
	Icarus Verilog
$end
$timescale
	1s
$end
$scope module tb $end
$var wire 1 ! w1 $end
$var reg 1 " r1 $end
$var reg 1 # r2 $end
$var reg 1 $ r3 $end
$var reg 1 % r4 $end
$scope module uut $end
$var wire 1 " A $end
$var wire 1 & AD $end
$var wire 1 ' An $end
$var wire 1 ( AnBC $end
$var wire 1 # B $end
$var wire 1 ) Bn $end
$var wire 1 $ C $end
$var wire 1 * Cn $end
$var wire 1 + CnD $end
$var wire 1 % D $end
$var wire 1 ! F $end
$upscope $end
$upscope $end
$enddefinitions $end
$comment Show the parameter values. $end
$dumpall
$end
#0
$dumpvars
0+
1*
1)
0(
1'
0&
0%
0$
0#
0"
1!
$end
#50
1+
1%
#100
0+
0*
0%
1$
#150
1%
#200
0!
1*
0)
0%
0$
1#
#250
1!
1+
1%
#300
0+
1(
0*
0%
1$
#350
1%
