iverilog/tobb/lab2/halfadder.v
module halfadder (
    input A,
    input B,
    output S,
    output C
);
    xor x1(S, A, B);
    and a1(C, A, B);
endmodule

iverilog/tobb/lab2/fulladder.v
module fulladder (
    input  A,
    input  B,
    input  Cin,
    output S,
    output Cout
);
  wire AxB, AnB1, AnB2;


  halfadder h1 (A,B,AxB,AnB2);

  halfadder h2 (AxB,Cin,S,AnB1);

  or o1 (Cout,AnB1,AnB2);
endmodule

iverilog/tobb/lab2/fulladdertb.v
module fulladdertb ();

reg r1, r2, r3;
wire w1, w2;

fulladder uut(
    .A(r1),
    .B(r2),
    .Cin(r3),
    .S(w1),
    .Cout(w2)
);

initial begin
    $dumpfile("fdmp.vcd");
    $dumpvars;
    r1 = 0; r2 = 0; r3 = 0; #10
    r1 = 0; r2 = 0; r3 = 1; #10
    r1 = 0; r2 = 1; r3 = 0; #10
    r1 = 0; r2 = 1; r3 = 1; #10
    r1 = 1; r2 = 0; r3 = 0; #10
    r1 = 1; r2 = 0; r3 = 1; #10
    r1 = 1; r2 = 1; r3 = 0; #10
    r1 = 1; r2 = 1; r3 = 1; #10
    $display(w1);
    $display(w2);
end

endmodule

iverilog/tobb/lab2/fdmp.vcd
$date
	Sun Dec  8 20:51:56 2024
$end
$version
	Icarus Verilog
$end
$timescale
	1s
$end
$scope module fulladdertb $end
$var wire 1 ! w2 $end
$var wire 1 " w1 $end
$var reg 1 # r1 $end
$var reg 1 $ r2 $end
$var reg 1 % r3 $end
$scope module uut $end
$var wire 1 # A $end
$var wire 1 $ B $end
$var wire 1 % Cin $end
$var wire 1 ! Cout $end
$var wire 1 " S $end
$var wire 1 & AxB $end
$var wire 1 ' AnB2 $end
$var wire 1 ( AnB1 $end
$scope module h1 $end
$var wire 1 # A $end
$var wire 1 $ B $end
$var wire 1 ' C $end
$var wire 1 & S $end
$upscope $end
$scope module h2 $end
$var wire 1 & A $end
$var wire 1 % B $end
$var wire 1 ( C $end
$var wire 1 " S $end
$upscope $end
$upscope $end
$upscope $end
$enddefinitions $end
#0
$dumpvars
0(
0'
0&
0%
0$
0#
0"
0!
$end
#10
1"
1%
#20
1&
0%
1$
#30
1!
0"
1(
1%
#40
0!
1"
0(
0%
0$
1#
#50
1!
0"
1(
1%
#60
0(
0&
1'
0%
1$
#70
1"
1%
