lab3/src/Adder3Bit.v
module Adder3Bit (
    input [2:0] num1,
    input [2:0] num2,
    output [2:0] Carry,
    output [2:0] sum
);

    xor (sum[0], num1[0], num2[0]);
    and (Carry[0], num1[0], num2[0]);

    wire num12[1:0];
    wire num12Carry[1:0], num1a2[1:0];

    xor (num12[0], num1[1], num2[1]);
    xor (sum[1], num12[0], Carry[0]);

    and (num12Carry[0], num12[0], Carry[0]);
    and (num1a2[0], num1[1], num2[1]);

    or (Carry[1], num12Carry[0], num1a2[0]);

    xor (num12[1], num1[2], num2[2]);
    xor (sum[2], num12[1], Carry[1]);

    and (num12Carry[1], num12[1], Carry[1]);
    and (num1a2[1], num1[2], num2[2]);

    or (Carry[2], num12Carry[1], num1a2[1]);

endmodule

lab3/src/tbAdder3Bit.v
module tbAdder3Bit ();

reg r1[2:0], r2[2:0];
wire w1[2:0], w2[2:0];

Adder3Bit uut(
    .num1[2:0](r1[2:0]),
    .num2[2:0](r2[2:0]),
    .sum[2:0](w1[2:0]),
    .Carry[2:0](w2[2:0])
);

initial begin
    $dumpfile("Admp.vcd");
    $dumpvars;
    r1 = 3'b000; r2 = 3'b000; #10
    r1 = 3'b001; r2 = 3'b001; #10
    r1 = 3'b010; r2 = 3'b010; #10
    r1 = 3'b100; r2 = 3'b100; #10
    r1 = 3'b011; r2 = 3'b011; #10
    r1 = 3'b101; r2 = 3'b101; #10
    r1 = 3'b110; r2 = 3'b110; #10
    r1 = 3'b111; r2 = 3'b111; #10
    $display(w1[2:0]);
    $display(w2[2:0]);
end

endmodule

labs/lab3/src/Admp.vcd
$date
	Sat Apr 13 14:50:50 2024
$end
$version
	Icarus Verilog
$end
$timescale
	1s
$end
$scope module tbAdder3Bit $end
$var wire 3 ! w2 [2:0] $end
$var wire 3 " w1 [2:0] $end
$var reg 3 # r1 [2:0] $end
$var reg 3 $ r2 [2:0] $end
$scope module uut $end
$var wire 3 % num1 [2:0] $end
$var wire 3 & num2 [2:0] $end
$var wire 3 ' sum [2:0] $end
$var wire 3 ( Carry [2:0] $end
$upscope $end
$upscope $end
$enddefinitions $end
$comment Show the parameter values. $end
$dumpall
$end
#0
$dumpvars
b0 (
b0 '
b0 &
b0 %
b0 $
b0 #
b0 "
b0 !
$end
#10
b10 "
b10 '
b1 !
b1 (
b1 $
b1 &
b1 #
b1 %
#20
b100 "
b100 '
b10 !
b10 (
b10 $
b10 &
b10 #
b10 %
#30
b0 "
b0 '
b100 !
b100 (
b100 $
b100 &
b100 #
b100 %
#40
b110 "
b110 '
b11 !
b11 (
b11 $
b11 &
b11 #
b11 %
#50
b10 "
b10 '
b101 !
b101 (
b101 $
b101 &
b101 #
b101 %
#60
b100 "
b100 '
b110 !
b110 (
b110 $
b110 &
b110 #
b110 %
#70
b110 "
b110 '
b111 !
b111 (
b111 $
b111 &
b111 #
b111 %
