labs/lab3/src/halfAdder.v
module halfAdder(
    input A, B,
    output S, C
);

xor(S, A, B);
and(C, A, B);

endmodule

labs/lab3/src/fullAdder.v
module fullAdder(
    input A, B, Z,
    output S, C
);
    wire W0, W1, W2;

halfAdder h0(A, B, W0, W1);
halfAdder h1(W0, Z, S, W2);

or(C, W1, W2);

endmodule

lab3/src/Adder3Bit.v
module Adder3Bit (
    input [2:0] A,
    input [2:0] B,
    output [3:0] C
);

wire c1, c2;
halfAdder a0(A[0], B[0], C[0], c1);

fullAdder a1(A[1], B[1], c1, C[1], c2);
fullAdder a2(A[2], B[2], c2, C[2], C[3]);
    


endmodule

labs/lab3/src/tb.v
module tb();

reg [2:0] A, B;
wire [3:0] C;
Adder3Bit uut(A, B, C);

initial begin
	$dumpfile("dmp.vcd");
	$dumpvars;

	A = 3'd0; B = 3'd7; #10;
	A = 3'd1; B = 3'd6; #10;
	A = 3'd2; B = 3'd5; #10;
	A = 3'd3; B = 3'd4; #10;
	A = 3'd4; B = 3'd3; #10;
	A = 3'd5; B = 3'd2; #10;
	A = 3'd6; B = 3'd1; #10;
	A = 3'd7; B = 3'd0; #10;

	A = 3'd0; B = 3'd0; #10;
	A = 3'd1; B = 3'd0; #10;
	A = 3'd2; B = 3'd0; #10;
	A = 3'd3; B = 3'd0; #10;
	A = 3'd4; B = 3'd0; #10;
	A = 3'd5; B = 3'd0; #10;
	A = 3'd6; B = 3'd0; #10;
	A = 3'd7; B = 3'd0; #10;

end

endmodule

labs/lab3/src/dmp.vcd
$date
	Fri May 03 11:28:11 2024
$end
$version
	Icarus Verilog
$end
$timescale
	1s
$end
$scope module tb $end
$var wire 4 ! C [3:0] $end
$var reg 3 " A [2:0] $end
$var reg 3 # B [2:0] $end
$scope module uut $end
$var wire 3 $ A [2:0] $end
$var wire 3 % B [2:0] $end
$var wire 1 & c2 $end
$var wire 1 ' c1 $end
$var wire 4 ( C [3:0] $end
$scope module a0 $end
$var wire 1 ) A $end
$var wire 1 * B $end
$var wire 1 ' C $end
$var wire 1 + S $end
$upscope $end
$scope module a1 $end
$var wire 1 , A $end
$var wire 1 - B $end
$var wire 1 & C $end
$var wire 1 ' Z $end
$var wire 1 . W2 $end
$var wire 1 / W1 $end
$var wire 1 0 W0 $end
$var wire 1 1 S $end
$scope module h0 $end
$var wire 1 , A $end
$var wire 1 - B $end
$var wire 1 / C $end
$var wire 1 0 S $end
$upscope $end
$scope module h1 $end
$var wire 1 0 A $end
$var wire 1 ' B $end
$var wire 1 . C $end
$var wire 1 1 S $end
$upscope $end
$upscope $end
$scope module a2 $end
$var wire 1 2 A $end
$var wire 1 3 B $end
$var wire 1 4 C $end
$var wire 1 & Z $end
$var wire 1 5 W2 $end
$var wire 1 6 W1 $end
$var wire 1 7 W0 $end
$var wire 1 8 S $end
$scope module h0 $end
$var wire 1 2 A $end
$var wire 1 3 B $end
$var wire 1 6 C $end
$var wire 1 7 S $end
$upscope $end
$scope module h1 $end
$var wire 1 7 A $end
$var wire 1 & B $end
$var wire 1 5 C $end
$var wire 1 8 S $end
$upscope $end
$upscope $end
$upscope $end
$upscope $end
$enddefinitions $end
$comment Show the parameter values. $end
$dumpall
$end
#0
$dumpvars
18
17
06
05
04
13
02
11
10
0/
0.
1-
0,
1+
1*
0)
b111 (
0'
0&
b111 %
b0 $
b111 #
b0 "
b111 !
$end
#10
0*
1)
b110 #
b110 %
b1 "
b1 $
#20
1*
0-
0)
1,
b101 #
b101 %
b10 "
b10 $
#30
0*
1)
b100 #
b100 %
b11 "
b11 $
#40
1*
1-
03
0)
0,
12
b11 #
b11 %
b100 "
b100 $
#50
0*
1)
b10 #
b10 %
b101 "
b101 $
#60
1*
0-
0)
1,
b1 #
b1 %
b110 "
b110 $
#70
0*
1)
b0 #
b0 %
b111 "
b111 $
#80
01
08
b0 !
b0 (
0+
00
07
0)
0,
02
b0 "
b0 $
#90
b1 !
b1 (
1+
1)
b1 "
b1 $
#100
11
b10 !
b10 (
0+
10
0)
1,
b10 "
b10 $
#110
b11 !
b11 (
1+
1)
b11 "
b11 $
#120
01
18
b100 !
b100 (
0+
00
17
0)
0,
12
b100 "
b100 $
#130
b101 !
b101 (
1+
1)
b101 "
b101 $
#140
11
b110 !
b110 (
0+
10
0)
1,
b110 "
b110 $
#150
b111 !
b111 (
1+
1)
b111 "
b111 $
